ssoacehpython/__init__.py
ssoacehpython/ssoclient.py
ssoacehpython-0.1.1.dist-info/LICENSE
ssoacehpython-0.1.1.dist-info/METADATA
ssoacehpython-0.1.1.dist-info/WHEEL
ssoacehpython-0.1.1.dist-info/top_level.txt
ssoacehpython-0.1.1.dist-info/RECORD
