Metadata-Version: 2.1
Name: ssoacehpython
Version: 0.1.1
Summary: SSO Aceh client for python language
Home-page: https://github.com/fuadarradhi/ssoacehpython
Author: Fuad Ar-Radhi
Author-email: fuad.arradhi@gmail.com
License: UNKNOWN
Platform: UNKNOWN
Classifier: Programming Language :: Python :: 3
Classifier: License :: OSI Approved :: MIT License
Classifier: Operating System :: OS Independent
Requires-Python: >=3.6
